repomate/__init__.py
repomate/__version.py
repomate/cli.py
repomate/command.py
repomate/config.py
repomate/exception.py
repomate/formatters.py
repomate/git.py
repomate/github_api.py
repomate/main.py
repomate/plugin.py
repomate/tuples.py
repomate/util.py
repomate/ext/__init__.py
repomate/ext/defaults.py
repomate/ext/javac.py
repomate/ext/pairwise.py
repomate/ext/pylint.py
repomate-1.1.3.data/scripts/repomate
repomate-1.1.3.dist-info/LICENSE
repomate-1.1.3.dist-info/METADATA
repomate-1.1.3.dist-info/WHEEL
repomate-1.1.3.dist-info/top_level.txt
repomate-1.1.3.dist-info/RECORD
