Metadata-Version: 2.1
Name: repomate
Version: 1.1.3
Summary: A CLI tool for managing large amounts of GitHub repositories
Home-page: https://github.com/slarse/repomate
Author: Simon Larsén
Author-email: slarse@kth.se
License: MIT
Download-URL: https://github.com/slarse/repomate/archive/v1.1.3.tar.gz
Platform: UNKNOWN
Classifier: Development Status :: 5 - Production/Stable
Classifier: Intended Audience :: Education
Classifier: Programming Language :: Python :: 3.5
Classifier: Programming Language :: Python :: 3.6
Classifier: Programming Language :: Python :: 3.7
Classifier: Programming Language :: Python :: Implementation :: CPython
Classifier: License :: OSI Approved :: MIT License
Classifier: Operating System :: POSIX
Requires-Python: >=3.5
Requires-Dist: appdirs
Requires-Dist: daiquiri
Requires-Dist: pygithub
Requires-Dist: colored
Requires-Dist: repomate-plug (>=0.4.1)
Provides-Extra: test
Requires-Dist: appdirs; extra == 'test'
Requires-Dist: daiquiri; extra == 'test'
Requires-Dist: pytest (>=4.0.0); extra == 'test'
Requires-Dist: pytest-cov (>=2.6.1); extra == 'test'
Requires-Dist: pytest-mock; extra == 'test'
Requires-Dist: codecov; extra == 'test'
